TeremokTSLib/__init__.py
TeremokTSLib/itertest/__init__.py
TeremokTSLib/itertest/optimization.py
TeremokTSLib/model/__init__.py
TeremokTSLib/model/minmax.py
TeremokTSLib/model/model.py
TeremokTSLib/model/support.py
TeremokTSLib-1.2.5.dist-info/LICENCE.txt
TeremokTSLib-1.2.5.dist-info/METADATA
TeremokTSLib-1.2.5.dist-info/WHEEL
TeremokTSLib-1.2.5.dist-info/top_level.txt
TeremokTSLib-1.2.5.dist-info/RECORD
