Metadata-Version: 2.1
Name: TeremokTSLib
Version: 1.2.5
Summary: Easy-to-use box ML solution for forcasting consumption
Home-page: https://teremok.ru/
Author: Alexander Nikitin
Author-email: sniknickitin@yandex.ru
License: MIT
Keywords: forcasting
Platform: UNKNOWN
Classifier: Development Status :: 4 - Beta
Classifier: License :: OSI Approved :: MIT License
Classifier: Programming Language :: Python :: 3
License-File: LICENCE.txt
Requires-Dist: catboost >=1.2.2
Requires-Dist: pandas >=2.1.4
Requires-Dist: numpy ==1.26.4
Requires-Dist: prophet >=1.1.5
Requires-Dist: statsmodels >=0.14.2
Requires-Dist: scikit-learn >=1.5.1
Requires-Dist: optuna >=3.5.0
